labpacks/connect.py
labpacks-0.1.9.dist-info/LICENSE
labpacks-0.1.9.dist-info/WHEEL
labpacks-0.1.9.dist-info/METADATA
labpacks-0.1.9.dist-info/RECORD
